linsys/__init__.py
linsys-0.0.0.dev0.dist-info/METADATA
linsys-0.0.0.dev0.dist-info/WHEEL
linsys-0.0.0.dev0.dist-info/top_level.txt
linsys-0.0.0.dev0.dist-info/RECORD
